Metadata-Version: 2.1
Name: Gbtestapi
Version: 0.1a10
Summary: GailBot API
Author-email: Muhammad Umair <muhammad.umair@tufts.edu>
Maintainer-email: Human Interaction Lab - Tufts University <hilab-dev@elist.tufts.edu>
License: MIT License
Project-URL: homepage, https://github.com/mumair01/GailBot
Project-URL: source, https://github.com/mumair01/GailBot
Project-URL: tracker, https://github.com/mumair01/GailBot/issues
Classifier: Intended Audience :: Science/Research
Classifier: Programming Language :: Python
Classifier: Programming Language :: Python :: 3
Classifier: Programming Language :: Python :: 3.8
Classifier: Topic :: Scientific/Engineering
Classifier: Operating System :: MacOS
Requires-Python: >=3.10
License-File: LICENSE
Requires-Dist: absl-py (==1.4.0)
Requires-Dist: aiohttp (==3.8.4)
Requires-Dist: aiosignal (==1.3.1)
Requires-Dist: alembic (==1.10.2)
Requires-Dist: altgraph (==0.17.3)
Requires-Dist: antlr4-python3-runtime (==4.9.3)
Requires-Dist: appdirs (==1.4.4)
Requires-Dist: asteroid-filterbanks (==0.4.0)
Requires-Dist: astunparse (==1.6.3)
Requires-Dist: async-timeout (==4.0.2)
Requires-Dist: attrs (==22.2.0)
Requires-Dist: audioread (==3.0.0)
Requires-Dist: auto-py-to-exe (==2.33.0)
Requires-Dist: backports.cached-property (==1.0.2)
Requires-Dist: black (==23.1.0)
Requires-Dist: bleach (==6.0.0)
Requires-Dist: boto3 (==1.26.105)
Requires-Dist: botocore (==1.29.105)
Requires-Dist: bottle (==0.12.25)
Requires-Dist: bottle-websocket (==0.2.9)
Requires-Dist: build (==0.10.0)
Requires-Dist: cachetools (==5.3.0)
Requires-Dist: certifi (==2022.12.7)
Requires-Dist: cffi (==1.15.1)
Requires-Dist: cfgv (==3.3.1)
Requires-Dist: charset-normalizer (==3.1.0)
Requires-Dist: click (==8.1.3)
Requires-Dist: cmaes (==0.9.1)
Requires-Dist: cmudict (==1.0.13)
Requires-Dist: colorama (==0.4.6)
Requires-Dist: colorlog (==6.7.0)
Requires-Dist: commonmark (==0.9.1)
Requires-Dist: contourpy (==1.0.7)
Requires-Dist: cPython (==0.0.6)
Requires-Dist: cryptography (==40.0.2)
Requires-Dist: cycler (==0.11.0)
Requires-Dist: Cython (==3.0.0)
Requires-Dist: dacite (==1.8.0)
Requires-Dist: decorator (==4.4.2)
Requires-Dist: dict-to-dataclass (==0.0.8)
Requires-Dist: distlib (==0.3.6)
Requires-Dist: dnspython (==2.3.0)
Requires-Dist: docopt (==0.6.2)
Requires-Dist: docutils (==0.19)
Requires-Dist: dotted-dict (==1.1.3)
Requires-Dist: dotwiz (==0.4.0)
Requires-Dist: dtw-python (==1.3.0)
Requires-Dist: Eel (==0.16.0)
Requires-Dist: einops (==0.3.2)
Requires-Dist: entrypoints (==0.4)
Requires-Dist: exceptiongroup (==1.1.1)
Requires-Dist: exif (==1.6.0)
Requires-Dist: ffmpeg-python (==0.2.0)
Requires-Dist: filelock (==3.10.0)
Requires-Dist: flake8 (==6.0.0)
Requires-Dist: flatbuffers (==23.3.3)
Requires-Dist: fonttools (==4.39.2)
Requires-Dist: frozenlist (==1.3.3)
Requires-Dist: fsspec (==2023.3.0)
Requires-Dist: future (==0.18.3)
Requires-Dist: gast (==0.5.3)
Requires-Dist: gevent (==22.10.2)
Requires-Dist: gevent-websocket (==0.10.1)
Requires-Dist: google-api-core (==2.11.0)
Requires-Dist: google-auth (==2.16.2)
Requires-Dist: google-auth-oauthlib (==0.4.6)
Requires-Dist: google-cloud-core (==2.3.2)
Requires-Dist: google-cloud-speech (==2.18.0)
Requires-Dist: google-pasta (==0.2.0)
Requires-Dist: googleapis-common-protos (==1.59.0)
Requires-Dist: greenlet (==2.0.2)
Requires-Dist: grpcio (==1.51.3)
Requires-Dist: grpcio-status (==1.51.3)
Requires-Dist: h5py (==3.8.0)
Requires-Dist: huggingface-hub (==0.13.3)
Requires-Dist: HyperPyYAML (==1.1.0)
Requires-Dist: ibm-cloud-sdk-core (==3.16.2)
Requires-Dist: ibm-watson (==7.0.0)
Requires-Dist: identify (==2.5.21)
Requires-Dist: idna (==3.4)
Requires-Dist: imageio (==2.26.1)
Requires-Dist: imageio-ffmpeg (==0.4.8)
Requires-Dist: importlib-metadata (==5.2.0)
Requires-Dist: importlib-resources (==5.12.0)
Requires-Dist: iniconfig (==2.0.0)
Requires-Dist: jaraco.classes (==3.2.3)
Requires-Dist: jedi (==0.18.1)
Requires-Dist: jmespath (==1.0.1)
Requires-Dist: joblib (==1.2.0)
Requires-Dist: julius (==0.2.7)
Requires-Dist: keras (==2.12.0)
Requires-Dist: keyring (==23.13.1)
Requires-Dist: kiwisolver (==1.4.4)
Requires-Dist: libclang (==15.0.6.1)
Requires-Dist: librosa (==0.9.2)
Requires-Dist: llvmlite (==0.39.1)
Requires-Dist: lxml (==4.9.2)
Requires-Dist: macholib (==1.16.2)
Requires-Dist: Mako (==1.2.4)
Requires-Dist: Markdown (==3.4.1)
Requires-Dist: MarkupSafe (==2.1.2)
Requires-Dist: matplotlib (==3.7.1)
Requires-Dist: mccabe (==0.7.0)
Requires-Dist: more-itertools (==9.1.0)
Requires-Dist: moviepy (==1.0.3)
Requires-Dist: mpmath (==1.3.0)
Requires-Dist: multidict (==6.0.4)
Requires-Dist: mypy-extensions (==1.0.0)
Requires-Dist: networkx (==2.8.8)
Requires-Dist: nodeenv (==1.7.0)
Requires-Dist: Nuitka (==1.5.3)
Requires-Dist: numba (==0.56.4)
Requires-Dist: numpy (==1.23.5)
Requires-Dist: oauthlib (==3.2.2)
Requires-Dist: omegaconf (==2.3.0)
Requires-Dist: openai-whisper (==20230314)
Requires-Dist: opt-einsum (==3.3.0)
Requires-Dist: optuna (==3.1.0)
Requires-Dist: ordered-set (==4.1.0)
Requires-Dist: packaging (==23.0)
Requires-Dist: pandas (==1.5.3)
Requires-Dist: parso (==0.8.3)
Requires-Dist: pathspec (==0.11.1)
Requires-Dist: pep517 (==0.13.0)
Requires-Dist: Pillow (==9.4.0)
Requires-Dist: pkginfo (==1.9.6)
Requires-Dist: platformdirs (==3.1.1)
Requires-Dist: pluggy (==1.0.0)
Requires-Dist: plum-py (==0.8.5)
Requires-Dist: pooch (==1.7.0)
Requires-Dist: pre-commit (==3.2.0)
Requires-Dist: primePy (==1.3)
Requires-Dist: proglog (==0.1.10)
Requires-Dist: proto-plus (==1.22.2)
Requires-Dist: protobuf (==4.22.1)
Requires-Dist: psutil (==5.9.4)
Requires-Dist: py (==1.11.0)
Requires-Dist: pyasn1 (==0.4.8)
Requires-Dist: pyasn1-modules (==0.2.8)
Requires-Dist: pycodestyle (==2.10.0)
Requires-Dist: pycparser (==2.21)
Requires-Dist: pydantic (==1.10.6)
Requires-Dist: pyDeprecate (==0.3.2)
Requires-Dist: pydub (==0.25.1)
Requires-Dist: pyee (==9.0.4)
Requires-Dist: PyExifTool (==0.5.5)
Requires-Dist: pyflakes (==3.0.1)
Requires-Dist: Pygments (==2.14.0)
Requires-Dist: pyheck (==0.1.5)
Requires-Dist: pyinstaller (==5.9.0)
Requires-Dist: pyinstaller-hooks-contrib (==2023.1)
Requires-Dist: PyJWT (==2.6.0)
Requires-Dist: pymongo (==4.3.3)
Requires-Dist: pyparsing (==3.0.9)
Requires-Dist: pyproject-hooks (==1.0.0)
Requires-Dist: PyQt6 (==6.4.2)
Requires-Dist: PyQt6-Qt6 (==6.4.3)
Requires-Dist: PyQt6-sip (==13.4.1)
Requires-Dist: pyqtconsole (==1.2.2)
Requires-Dist: pytest (==7.2.2)
Requires-Dist: python-configuration (==0.8.2)
Requires-Dist: python-dateutil (==2.8.1)
Requires-Dist: pytorch-lightning (==1.6.3)
Requires-Dist: pytorch-metric-learning (==1.7.3)
Requires-Dist: pytz (==2022.7.1)
Requires-Dist: PyYAML (==6.0)
Requires-Dist: QtPy (==2.2.0)
Requires-Dist: readme-renderer (==37.3)
Requires-Dist: regex (==2022.10.31)
Requires-Dist: requests (==2.28.2)
Requires-Dist: requests-oauthlib (==1.3.1)
Requires-Dist: requests-toolbelt (==0.10.1)
Requires-Dist: resampy (==0.4.2)
Requires-Dist: rfc3986 (==2.0.0)
Requires-Dist: rich (==12.6.0)
Requires-Dist: rsa (==4.9)
Requires-Dist: ruamel.yaml (==0.17.21)
Requires-Dist: ruamel.yaml.clib (==0.2.7)
Requires-Dist: s3transfer (==0.6.0)
Requires-Dist: sacremoses (==0.0.53)
Requires-Dist: scikit-learn (==1.2.2)
Requires-Dist: scipy (==1.10.1)
Requires-Dist: selenium (==3.10.0)
Requires-Dist: semantic-version (==2.10.0)
Requires-Dist: semver (==2.13.0)
Requires-Dist: sentencepiece (==0.1.97)
Requires-Dist: setuptools-rust (==1.5.2)
Requires-Dist: shellingham (==1.5.0.post1)
Requires-Dist: simplejson (==3.18.4)
Requires-Dist: singledispatchmethod (==1.0)
Requires-Dist: six (==1.16.0)
Requires-Dist: sortedcontainers (==2.4.0)
Requires-Dist: sounddevice (==0.4.6)
Requires-Dist: soundfile (==0.12.1)
Requires-Dist: speechbrain (==0.5.13)
Requires-Dist: SQLAlchemy (==2.0.7)
Requires-Dist: syllable (==0.1.0)
Requires-Dist: syllables (==1.0.7)
Requires-Dist: sympy (==1.11.1)
Requires-Dist: tabulate (==0.9.0)
Requires-Dist: tensorboard (==2.12.0)
Requires-Dist: tensorboard-data-server (==0.7.0)
Requires-Dist: tensorboard-plugin-wit (==1.8.1)
Requires-Dist: tensorflow-estimator (==2.12.0)
Requires-Dist: termcolor (==2.2.0)
Requires-Dist: threadpoolctl (==3.1.0)
Requires-Dist: tiktoken (==0.3.1)
Requires-Dist: tokenizers (==0.13.2)
Requires-Dist: toml (==0.10.2)
Requires-Dist: tomli (==2.0.1)
Requires-Dist: torch (==1.13.1)
Requires-Dist: torch-audiomentations (==0.11.0)
Requires-Dist: torch-pitch-shift (==1.2.2)
Requires-Dist: torchaudio (==0.13.1)
Requires-Dist: torchmetrics (==0.11.4)
Requires-Dist: torchvision (==0.14.1)
Requires-Dist: tqdm (==4.65.0)
Requires-Dist: transformers (==4.27.2)
Requires-Dist: twine (==4.0.2)
Requires-Dist: typed-ast (==1.5.4)
Requires-Dist: typer (==0.7.0)
Requires-Dist: typing-extensions (==4.5.0)
Requires-Dist: urllib3 (==1.26.15)
Requires-Dist: userpaths (==0.1.3)
Requires-Dist: validators (==0.20.0)
Requires-Dist: virtualenv (==20.21.0)
Requires-Dist: wcwidth (==0.2.6)
Requires-Dist: webencodings (==0.5.1)
Requires-Dist: websocket-client (==1.1.0)
Requires-Dist: Werkzeug (==2.2.3)
Requires-Dist: whichcraft (==0.6.1)
Requires-Dist: wrapt (==1.15.0)
Requires-Dist: xattr (==0.10.1)
Requires-Dist: yamllint (==1.29.0)
Requires-Dist: yarl (==1.8.2)
Requires-Dist: zipp (==3.15.0)
Requires-Dist: zope.event (==4.6)
Requires-Dist: zope.interface (==6.0)
Requires-Dist: zstandard (==0.20.0)
Provides-Extra: dev
Requires-Dist: pytest ; extra == 'dev'
Requires-Dist: pytest-cov ; extra == 'dev'
Requires-Dist: pytest-timeout ; extra == 'dev'
Requires-Dist: pytest-xdist ; extra == 'dev'
Requires-Dist: ipython ; extra == 'dev'
